XcomLAN/__init__.py
XcomLAN/appendix.py
XcomLAN/property_format.py
XcomLAN/scom.py
XcomLAN/device/__init__.py
XcomLAN/device/addresses.py
XcomLAN/device/base_device.py
XcomLAN/device/bsp.py
XcomLAN/device/device_factory.py
XcomLAN/device/device_type.py
XcomLAN/device/rcc.py
XcomLAN/device/vario_string.py
XcomLAN/device/vario_track.py
XcomLAN/device/xtender.py
XcomLAN/node_manager/__init__.py
XcomLAN/node_manager/node_manager.py
XcomLAN/node_manager/node_observer.py
XcomLAN/thingsboard/__init__.py
XcomLAN/thingsboard/thingsboard_client.py
XcomLAN-0.0.1.dist-info/LICENSE.md
XcomLAN-0.0.1.dist-info/METADATA
XcomLAN-0.0.1.dist-info/WHEEL
XcomLAN-0.0.1.dist-info/top_level.txt
XcomLAN-0.0.1.dist-info/RECORD
