Metadata-Version: 2.1
Name: XcomLAN
Version: 0.0.1
Summary: Python library to access Studer-Innotec Xcom-LAN/Xcom-232i node through (SCOM) Xtender Serial Protocol over a TCP/IP Network connection.
Home-page: https://pypi.org/project/XcomLAN/
Author: Mustafa M. A. U. AbuGhazy
Author-email: moustafa.abu.ghazy@gmail.com
Maintainer-email: moustafa.abu.ghazy@gmail.com
License: MIT
Project-URL: Documentation, https://mustafa-abu-ghazy.github.io/XcomLAN/
Project-URL: Issues tracker, https://github.com/mustafa-abu-ghazy/XcomLAN/issues
Project-URL: Source Code, https://github.com/mustafa-abu-ghazy/XcomLAN
Platform: any
Classifier: Development Status :: 4 - Beta
Classifier: Intended Audience :: Developers
Classifier: Intended Audience :: Education
Classifier: Intended Audience :: Science/Research
Classifier: Intended Audience :: System Administrators
Classifier: License :: OSI Approved :: MIT License
Classifier: Natural Language :: English
Classifier: Operating System :: OS Independent
Classifier: Programming Language :: Cython
Classifier: Programming Language :: Python :: 3
Classifier: Programming Language :: Python :: 3.6
Classifier: Programming Language :: Python :: 3.7
Classifier: Programming Language :: Python :: 3.8
Classifier: Programming Language :: Python :: 3.9
Classifier: Programming Language :: Python :: 3.10
Classifier: Topic :: Communications
Classifier: Topic :: Scientific/Engineering
Classifier: Topic :: Scientific/Engineering :: Visualization
Classifier: Topic :: Software Development
Classifier: Topic :: Software Development :: Libraries
Classifier: Topic :: Software Development :: Libraries :: Python Modules
Classifier: Topic :: System :: Monitoring
Classifier: Topic :: Terminals :: Serial
Requires-Python: >=3.6
License-File: LICENSE.md
Requires-Dist: scom (==0.7.3)
Requires-Dist: Cython
Requires-Dist: pyserial (>=3.5)
Requires-Dist: python-dotenv
Provides-Extra: thingsboard
Requires-Dist: tb-mqtt-client ; extra == 'thingsboard'
